[{"index": 0, "words": ["megan", "black", "ponytail", "friend", "game", "panel", "year", "beret", "number", "phone"]}, {"index": 1, "words": ["stapl", "momentum", "len", "megan", "cat", "repair", "beret", "ponytail", "pointer", "black"]}, {"index": 2, "words": ["cabl", "jack", "geek", "ingredi", "pump", "verb", "guest", "sister", "factori", "weekend"]}, {"index": 3, "words": ["barrel", "bowl", "polar", "weekend", "screenshot", "float", "dozen", "flowchart", "flash", "sleep"]}, {"index": 4, "words": ["gold", "megan", "michael", "pool", "sheet", "love", "backpack", "feynman", "peni", "bird"]}, {"index": 5, "words": ["band", "fluid", "song", "wikipedia", "megan", "bush", "word", "game", "monster", "music"]}, {"index": 6, "words": ["elev", "twitter", "megan", "reddit", "cabl", "friend", "kernel", "river", "user", "lake"]}, {"index": 7, "words": ["skateboard", "senat", "steve", "firefli", "escal", "summer", "paul", "democrat", "republican", "adam"]}, {"index": 8, "words": ["chess", "pok\u00e9mon", "knight", "hors", "basketbal", "sister", "player", "captur", "piec", "board"]}, {"index": 9, "words": ["virus", "backup", "keyboard", "chip", "belt", "dougla", "drone", "black", "beret", "ghost"]}]